expert_training/README.txt
expert_training/__init__.py
expert_training/sft_trainer.py
merge/__init__.py
merge/config.py
merge/main_merging.py
merge/mask_weights_utils.py
merge/merging_methods.py
merge/stat_task_vector_signal.py
merge/task_vector.py
merge/utils.py
merging_eval-0.1.4.dist-info/licenses/LICENSE
merging_eval-0.1.4.dist-info/METADATA
merging_eval-0.1.4.dist-info/WHEEL
merging_eval-0.1.4.dist-info/entry_points.txt
merging_eval-0.1.4.dist-info/top_level.txt
merging_eval-0.1.4.dist-info/RECORD
