Metadata-Version: 2.4
Name: merging-eval
Version: 0.1.4
Summary: Model Merging Scaling Laws in Large Language Models - Empirical scaling laws for language model merging measured by cross-entropy
Author-email: Merging-EVAL Team <maxuan1798@gmail.com>
License: MIT License
Project-URL: Homepage, https://github.com/Merging-EVAL/Merging-EVAL
Project-URL: Documentation, https://github.com/Merging-EVAL/Merging-EVAL#readme
Project-URL: Repository, https://github.com/Merging-EVAL/Merging-EVAL
Project-URL: Issues, https://github.com/Merging-EVAL/Merging-EVAL/issues
Keywords: llm,model-merging,scaling-laws,language-models,cross-entropy
Classifier: Development Status :: 4 - Beta
Classifier: Intended Audience :: Science/Research
Classifier: License :: OSI Approved :: MIT License
Classifier: Operating System :: OS Independent
Classifier: Programming Language :: Python :: 3
Classifier: Programming Language :: Python :: 3.8
Classifier: Programming Language :: Python :: 3.9
Classifier: Programming Language :: Python :: 3.10
Classifier: Programming Language :: Python :: 3.11
Classifier: Programming Language :: Python :: 3.12
Classifier: Topic :: Scientific/Engineering :: Artificial Intelligence
Requires-Python: >=3.8
License-File: LICENSE
Requires-Dist: torch>=2.0.0
Requires-Dist: transformers>=4.30.0
Requires-Dist: datasets>=2.12.0
Requires-Dist: accelerate>=0.20.0
Requires-Dist: pandas>=2.0.0
Requires-Dist: tqdm>=4.65.0
Requires-Dist: requests>=2.31.0
Provides-Extra: full
Requires-Dist: torch==2.6.0; extra == "full"
Requires-Dist: torchaudio==2.6.0; extra == "full"
Requires-Dist: torchvision==0.21.0; extra == "full"
Requires-Dist: transformers==4.50.1; extra == "full"
Requires-Dist: datasets==3.4.1; extra == "full"
Requires-Dist: tokenizers==0.21.1; extra == "full"
Requires-Dist: huggingface-hub==0.29.3; extra == "full"
Requires-Dist: safetensors==0.5.3; extra == "full"
Requires-Dist: pyarrow==19.0.1; extra == "full"
Requires-Dist: swanlab>=0.3.0; extra == "full"
Requires-Dist: bitsandbytes==0.45.4; extra == "full"
Requires-Dist: peft==0.15.0; extra == "full"
Requires-Dist: deepspeed==0.16.4; extra == "full"
Requires-Dist: vllm==0.8.2; extra == "full"
Requires-Dist: triton==3.2.0; extra == "full"
Requires-Dist: xformers==0.0.29.post2; extra == "full"
Requires-Dist: flashinfer-python==0.2.3; extra == "full"
Requires-Dist: ninja==1.11.1.4; extra == "full"
Requires-Dist: compressed-tensors==0.9.2; extra == "full"
Requires-Dist: gguf==0.10.0; extra == "full"
Requires-Dist: trl==0.15.2; extra == "full"
Requires-Dist: unsloth==2025.3.18; extra == "full"
Requires-Dist: unsloth_zoo==2025.3.16; extra == "full"
Requires-Dist: outlines==0.1.11; extra == "full"
Requires-Dist: outlines_core==0.1.26; extra == "full"
Requires-Dist: lm-format-enforcer==0.10.11; extra == "full"
Requires-Dist: llguidance==0.7.10; extra == "full"
Requires-Dist: xgrammar==0.1.16; extra == "full"
Requires-Dist: diffusers==0.32.2; extra == "full"
Requires-Dist: opencv-python-headless==4.11.0.86; extra == "full"
Requires-Dist: pillow==11.1.0; extra == "full"
Requires-Dist: cupy-cuda12x==13.4.1; extra == "full"
Requires-Dist: nvidia-ml-py==12.570.86; extra == "full"
Requires-Dist: fastapi==0.115.12; extra == "full"
Requires-Dist: uvicorn==0.34.0; extra == "full"
Requires-Dist: starlette==0.46.1; extra == "full"
Requires-Dist: pydantic==2.10.6; extra == "full"
Requires-Dist: wandb==0.19.8; extra == "full"
Requires-Dist: prometheus-client==0.21.1; extra == "full"
Requires-Dist: prometheus-fastapi-instrumentator==7.1.0; extra == "full"
Requires-Dist: nvitop==1.4.2; extra == "full"
Requires-Dist: ray==2.44.0; extra == "full"
Requires-Dist: scipy==1.15.2; extra == "full"
Requires-Dist: scikit-learn==1.6.1; extra == "full"
Requires-Dist: numba==0.60.0; extra == "full"
Requires-Dist: llvmlite==0.43.0; extra == "full"
Requires-Dist: matplotlib==3.10.1; extra == "full"
Requires-Dist: seaborn==0.13.2; extra == "full"
Requires-Dist: click==8.1.8; extra == "full"
Requires-Dist: rich==13.9.4; extra == "full"
Requires-Dist: typer==0.15.2; extra == "full"
Requires-Dist: pyyaml==6.0.2; extra == "full"
Requires-Dist: python-dotenv==1.1.0; extra == "full"
Requires-Dist: httpx==0.28.1; extra == "full"
Requires-Dist: aiohttp==3.11.14; extra == "full"
Requires-Dist: openai==1.68.2; extra == "full"
Requires-Dist: einops==0.8.1; extra == "full"
Requires-Dist: sentencepiece==0.2.0; extra == "full"
Requires-Dist: tiktoken==0.9.0; extra == "full"
Requires-Dist: protobuf==3.20.3; extra == "full"
Requires-Dist: psutil==7.0.0; extra == "full"
Requires-Dist: filelock==3.18.0; extra == "full"
Requires-Dist: regex==2024.11.6; extra == "full"
Requires-Dist: packaging==24.2; extra == "full"
Requires-Dist: fsspec==2024.12.0; extra == "full"
Dynamic: license-file
